artisan_engine/__init__.py
artisan_engine/adapter.py
artisan_engine/config.py
artisan_engine/exceptions.py
artisan_engine/models.py
artisan_engine/schemas.py
artisan_engine-0.1.0.dist-info/licenses/LICENSE
artisan_engine-0.1.0.dist-info/METADATA
artisan_engine-0.1.0.dist-info/WHEEL
artisan_engine-0.1.0.dist-info/top_level.txt
artisan_engine-0.1.0.dist-info/RECORD
