Metadata-Version: 2.4
Name: artisan-engine
Version: 0.1.0
Summary: A production-grade, OpenAI-compatible API layer for local LLMs with guaranteed structured output.
Author-email: Amit Afre <your.email@example.com>
License-Expression: Apache-2.0
Project-URL: Homepage, https://github.com/aafre/artisan-engine
Project-URL: Repository, https://github.com/aafre/artisan-engine
Classifier: Programming Language :: Python :: 3
Classifier: Operating System :: OS Independent
Classifier: Topic :: Scientific/Engineering :: Artificial Intelligence
Requires-Python: >=3.12
License-File: LICENSE
Requires-Dist: llama-cpp-python>=0.3.14
Requires-Dist: numba>=0.61.2
Requires-Dist: outlines>=1.2.1
Requires-Dist: pydantic>=2.11.7
Requires-Dist: pydantic-settings>=2.0.0
Requires-Dist: fastapi>=0.115.0
Requires-Dist: uvicorn[standard]>=0.32.0
Requires-Dist: python-multipart>=0.0.12
Requires-Dist: httpx>=0.28.1
Requires-Dist: python-dotenv>=1.0.0
Requires-Dist: openai>=1.99.5
Provides-Extra: dev
Requires-Dist: pytest>=8.0.0; extra == "dev"
Requires-Dist: pytest-asyncio>=0.21.0; extra == "dev"
Requires-Dist: httpx>=0.24.0; extra == "dev"
Requires-Dist: ruff>=0.7.0; extra == "dev"
Dynamic: license-file
